muvi/__init__.py
muvi/core/__init__.py
muvi/core/callbacks.py
muvi/core/early_stopping.py
muvi/core/gpu.py
muvi/core/index.py
muvi/core/models.py
muvi/core/synthetic.py
muvi/log.conf
muvi/tools/__init__.py
muvi/tools/cache.py
muvi/tools/external.py
muvi/tools/feature_sets.py
muvi/tools/plotting.py
muvi/tools/utils.py
muvi-0.1.5.dist-info/LICENSE
muvi-0.1.5.dist-info/METADATA
muvi-0.1.5.dist-info/WHEEL
muvi-0.1.5.dist-info/RECORD
