Metadata-Version: 2.1
Name: muvi
Version: 0.1.5
Summary: MuVI: A multi-view latent variable model with domain-informed structured sparsity for integrating noisy feature sets.
Home-page: https://github.com/MLO-lab/MuVI
Keywords: multi-view,multi-omics,feature sets,latent variable model,structured sparsity,variational inference,single-cell
Author: Arber Qoku
Author-email: arber.qoku@dkfz-heidelberg.com
Requires-Python: >=3.9,<3.11
Classifier: Programming Language :: Python :: 3
Classifier: Programming Language :: Python :: 3.9
Classifier: Programming Language :: Python :: 3.10
Requires-Dist: dill (>=0.3.7,<0.4.0)
Requires-Dist: igraph (>=0.11.5,<0.12.0)
Requires-Dist: kneed (>=0.8.5,<0.9.0)
Requires-Dist: leidenalg (>=0.10.2,<0.11.0)
Requires-Dist: mudata (>=0.2.3,<0.3.0)
Requires-Dist: numpy (>=1.26.1,<2.0.0)
Requires-Dist: pandas (>=2.1.1,<3.0.0)
Requires-Dist: pyro-ppl (==1.8.6)
Requires-Dist: scanpy (>=1.9.5,<2.0.0)
Requires-Dist: scikit-learn (>=1.3.1,<2.0.0)
Requires-Dist: scipy (>=1.11.3,<2.0.0)
Requires-Dist: seaborn (>=0.13.0,<0.14.0)
Requires-Dist: statsmodels (>=0.14.0,<0.15.0)
Requires-Dist: tabulate (>=0.9.0,<0.10.0)
Requires-Dist: tensordict (>=0.4.0,<0.5.0)
Requires-Dist: torch (>=2.3.0,<3.0.0)
Requires-Dist: tqdm (>=4.66.1,<5.0.0)
Project-URL: Repository, https://github.com/MLO-lab/MuVI
